simpleatm/__init__.py
simpleatm-0.1.0.dist-info/LICENSE
simpleatm-0.1.0.dist-info/WHEEL
simpleatm-0.1.0.dist-info/METADATA
simpleatm-0.1.0.dist-info/RECORD
