Metadata-Version: 2.1
Name: simpleatm
Version: 0.1.0
Summary: Lightweight Python package for calculating the atmospheric transmission
Home-page: https://github.com/deshima-dev/simpleatm
License: MIT
Author: Akio Taniguchi
Author-email: taniguchi@a.phys.nagoya-u.ac.jp
Maintainer: Yohei Togami
Maintainer-email: y.togami@a.phys.nagoya-u.ac.jp
Requires-Python: >=3.6,<4.0
Classifier: License :: OSI Approved :: MIT License
Classifier: Programming Language :: Python :: 3
Classifier: Programming Language :: Python :: 3.6
Classifier: Programming Language :: Python :: 3.7
Classifier: Programming Language :: Python :: 3.8
Classifier: Programming Language :: Python :: 3.9
Requires-Dist: xarray (>=0.15,<0.16)
